moviefetcher/moviefetcher.py
moviefetcher-2.1.0.dist-info/LICENSE
moviefetcher-2.1.0.dist-info/METADATA
moviefetcher-2.1.0.dist-info/WHEEL
moviefetcher-2.1.0.dist-info/top_level.txt
moviefetcher-2.1.0.dist-info/RECORD
