Metadata-Version: 2.1
Name: moviefetcher
Version: 2.1.0
Summary: This Library allows Developers to Get all top 100 Movies with Rating in JSON and CSV File
Home-page: https://github.com/soumilshah1995/weatherUSA
Author: Soumil Nitin Shah
Author-email: soushah@my.bridgeport.edu
License: MIT
Platform: UNKNOWN
Classifier: License :: OSI Approved :: MIT License
Classifier: Programming Language :: Python :: 3
Classifier: Programming Language :: Python :: 3.7
Requires-Dist: requests
Requires-Dist: pandas (==0.24.0)
